boreholeio/__init__.py
boreholeio/errors.py
boreholeio/data/__init__.py
boreholeio/data/axes.py
boreholeio/data/common.py
boreholeio/data/measurement_array.py
boreholeio/files/__init__.py
boreholeio/files/strided_array_file.py
boreholeio-0.1.0.dist-info/METADATA
boreholeio-0.1.0.dist-info/WHEEL
boreholeio-0.1.0.dist-info/licenses/LICENSE
boreholeio-0.1.0.dist-info/RECORD
