Metadata-Version: 2.4
Name: boreholeio
Version: 0.1.0
Summary: A library for interacting with borehole.io, a subsurface data management, delivery and visualisation platform.
Project-URL: Homepage, https://git.alt.lu/alt/borehole.io-python
Project-URL: Issues, https://git.alt.lu/alt/borehole.io-python/issues
Author-email: Advanced Logic Technology <support@alt.lu>
License-File: LICENSE
Classifier: Development Status :: 1 - Planning
Classifier: License :: OSI Approved :: BSD License
Classifier: Operating System :: OS Independent
Classifier: Programming Language :: Python :: 3
Requires-Python: >=3.8
Requires-Dist: numpy~=1.20
